{
	"configurations" : 
	[
		{
			"directories" : 
			[
				{
					"build" : ".",
					"childIndexes" : 
					[
						1,
						2
					],
					"hasInstallRule" : true,
					"jsonFile" : "directory-.-Debug-d0094a50bb2071803777.json",
					"minimumCMakeVersion" : 
					{
						"string" : "3.25"
					},
					"projectIndex" : 0,
					"source" : ".",
					"targetIndexes" : 
					[
						5,
						6
					]
				},
				{
					"build" : "nlohmann_json",
					"jsonFile" : "directory-nlohmann_json-Debug-96c3a9916b67f0e9629f.json",
					"minimumCMakeVersion" : 
					{
						"string" : "3.1"
					},
					"parentIndex" : 0,
					"projectIndex" : 1,
					"source" : "nlohmann_json"
				},
				{
					"build" : "tests",
					"childIndexes" : 
					[
						3
					],
					"hasInstallRule" : true,
					"jsonFile" : "directory-tests-Debug-70e4927a02b591d5c1f8.json",
					"minimumCMakeVersion" : 
					{
						"string" : "3.25"
					},
					"parentIndex" : 0,
					"projectIndex" : 2,
					"source" : "tests",
					"targetIndexes" : 
					[
						4
					]
				},
				{
					"build" : "_deps/googletest-build",
					"childIndexes" : 
					[
						4
					],
					"hasInstallRule" : true,
					"jsonFile" : "directory-_deps.googletest-build-Debug-ded26adebee9516e95c3.json",
					"minimumCMakeVersion" : 
					{
						"string" : "2.8.12"
					},
					"parentIndex" : 2,
					"projectIndex" : 3,
					"source" : "cmake-build-debug/_deps/googletest-src"
				},
				{
					"build" : "_deps/googletest-build/googlemock",
					"childIndexes" : 
					[
						5
					],
					"hasInstallRule" : true,
					"jsonFile" : "directory-_deps.googletest-build.googlemock-Debug-1e2dd9836afa402b2b8a.json",
					"minimumCMakeVersion" : 
					{
						"string" : "2.8.12"
					},
					"parentIndex" : 3,
					"projectIndex" : 4,
					"source" : "cmake-build-debug/_deps/googletest-src/googlemock",
					"targetIndexes" : 
					[
						0,
						1
					]
				},
				{
					"build" : "_deps/googletest-build/googletest",
					"hasInstallRule" : true,
					"jsonFile" : "directory-_deps.googletest-build.googletest-Debug-7abe1983488bd3b5bc81.json",
					"minimumCMakeVersion" : 
					{
						"string" : "2.8.12"
					},
					"parentIndex" : 4,
					"projectIndex" : 5,
					"source" : "cmake-build-debug/_deps/googletest-src/googletest",
					"targetIndexes" : 
					[
						2,
						3
					]
				}
			],
			"name" : "Debug",
			"projects" : 
			[
				{
					"childIndexes" : 
					[
						1,
						2
					],
					"directoryIndexes" : 
					[
						0
					],
					"name" : "search_engine1",
					"targetIndexes" : 
					[
						5,
						6
					]
				},
				{
					"directoryIndexes" : 
					[
						1
					],
					"name" : "nlohmann_json",
					"parentIndex" : 0
				},
				{
					"childIndexes" : 
					[
						3
					],
					"directoryIndexes" : 
					[
						2
					],
					"name" : "search_engine1_tests",
					"parentIndex" : 0,
					"targetIndexes" : 
					[
						4
					]
				},
				{
					"childIndexes" : 
					[
						4
					],
					"directoryIndexes" : 
					[
						3
					],
					"name" : "googletest-distribution",
					"parentIndex" : 2
				},
				{
					"childIndexes" : 
					[
						5
					],
					"directoryIndexes" : 
					[
						4
					],
					"name" : "gmock",
					"parentIndex" : 3,
					"targetIndexes" : 
					[
						0,
						1
					]
				},
				{
					"directoryIndexes" : 
					[
						5
					],
					"name" : "gtest",
					"parentIndex" : 4,
					"targetIndexes" : 
					[
						2,
						3
					]
				}
			],
			"targets" : 
			[
				{
					"directoryIndex" : 4,
					"id" : "gmock::@0f7bb11d64f3678238c7",
					"jsonFile" : "target-gmock-Debug-e95a136062efb61e3127.json",
					"name" : "gmock",
					"projectIndex" : 4
				},
				{
					"directoryIndex" : 4,
					"id" : "gmock_main::@0f7bb11d64f3678238c7",
					"jsonFile" : "target-gmock_main-Debug-02012fb560d98d4c458e.json",
					"name" : "gmock_main",
					"projectIndex" : 4
				},
				{
					"directoryIndex" : 5,
					"id" : "gtest::@1ea2dfc0605fe3ab2a3f",
					"jsonFile" : "target-gtest-Debug-305e2df1e1b3d7f96529.json",
					"name" : "gtest",
					"projectIndex" : 5
				},
				{
					"directoryIndex" : 5,
					"id" : "gtest_main::@1ea2dfc0605fe3ab2a3f",
					"jsonFile" : "target-gtest_main-Debug-f3e7b93d2ef857a431cf.json",
					"name" : "gtest_main",
					"projectIndex" : 5
				},
				{
					"directoryIndex" : 2,
					"id" : "search_engine1_tests::@a44f0ac069e85531cdee",
					"jsonFile" : "target-search_engine1_tests-Debug-1ca93dc3cf476d509b49.json",
					"name" : "search_engine1_tests",
					"projectIndex" : 2
				},
				{
					"directoryIndex" : 0,
					"id" : "search_engine_executable::@6890427a1f51a3e7e1df",
					"jsonFile" : "target-search_engine_executable-Debug-cf71cf6068d9d734c8fd.json",
					"name" : "search_engine_executable",
					"projectIndex" : 0
				},
				{
					"directoryIndex" : 0,
					"id" : "search_engine_lib::@6890427a1f51a3e7e1df",
					"jsonFile" : "target-search_engine_lib-Debug-4f646efbd31622971bb9.json",
					"name" : "search_engine_lib",
					"projectIndex" : 0
				}
			]
		}
	],
	"kind" : "codemodel",
	"paths" : 
	{
		"build" : "C:/skillbox-projects/profession-c-plus-plus/search_engine1/cmake-build-debug",
		"source" : "C:/skillbox-projects/profession-c-plus-plus/search_engine1"
	},
	"version" : 
	{
		"major" : 2,
		"minor" : 7
	}
}
